{
    "key": "group_65be97ef704b9",
    "title": "Информация о компании",
    "fields": [
        {
            "key": "field_65be9802004c9",
            "label": "Логотип",
            "name": "logo",
            "aria-label": "",
            "type": "group",
            "instructions": "",
            "required": 0,
            "conditional_logic": 0,
            "wrapper": {
                "width": "",
                "class": "",
                "id": ""
            },
            "layout": "table",
            "sub_fields": [
                {
                    "key": "field_65be980e004ca",
                    "label": "Мобильная версия",
                    "name": "mobile",
                    "aria-label": "",
                    "type": "file",
                    "instructions": "",
                    "required": 0,
                    "conditional_logic": 0,
                    "wrapper": {
                        "width": "",
                        "class": "",
                        "id": ""
                    },
                    "return_format": "array",
                    "library": "all",
                    "min_size": "",
                    "max_size": "",
                    "mime_types": ""
                },
                {
                    "key": "field_65be981c004cb",
                    "label": "Десктопная версия",
                    "name": "desktop",
                    "aria-label": "",
                    "type": "file",
                    "instructions": "",
                    "required": 0,
                    "conditional_logic": 0,
                    "wrapper": {
                        "width": "",
                        "class": "",
                        "id": ""
                    },
                    "return_format": "array",
                    "library": "all",
                    "min_size": "",
                    "max_size": "",
                    "mime_types": ""
                }
            ]
        },
        {
            "key": "field_65be9837004cc",
            "label": "Контакты",
            "name": "contacts",
            "aria-label": "",
            "type": "group",
            "instructions": "",
            "required": 0,
            "conditional_logic": 0,
            "wrapper": {
                "width": "",
                "class": "",
                "id": ""
            },
            "layout": "row",
            "sub_fields": [
                {
                    "key": "field_65be984f004cd",
                    "label": "Телефон",
                    "name": "phone",
                    "aria-label": "",
                    "type": "text",
                    "instructions": "",
                    "required": 0,
                    "conditional_logic": 0,
                    "wrapper": {
                        "width": "",
                        "class": "",
                        "id": ""
                    },
                    "default_value": "",
                    "maxlength": "",
                    "placeholder": "",
                    "prepend": "",
                    "append": ""
                },
                {
                    "key": "field_65be985c004ce",
                    "label": "Email",
                    "name": "email",
                    "aria-label": "",
                    "type": "email",
                    "instructions": "",
                    "required": 0,
                    "conditional_logic": 0,
                    "wrapper": {
                        "width": "",
                        "class": "",
                        "id": ""
                    },
                    "default_value": "",
                    "placeholder": "",
                    "prepend": "",
                    "append": ""
                },
                {
                    "key": "field_65be9864004cf",
                    "label": "Адрес",
                    "name": "address",
                    "aria-label": "",
                    "type": "text",
                    "instructions": "",
                    "required": 0,
                    "conditional_logic": 0,
                    "wrapper": {
                        "width": "",
                        "class": "",
                        "id": ""
                    },
                    "default_value": "",
                    "maxlength": "",
                    "placeholder": "",
                    "prepend": "",
                    "append": ""
                },
                {
                    "key": "field_65be9872004d0",
                    "label": "Ссылка на карту",
                    "name": "map_link",
                    "aria-label": "",
                    "type": "url",
                    "instructions": "",
                    "required": 0,
                    "conditional_logic": 0,
                    "wrapper": {
                        "width": "",
                        "class": "",
                        "id": ""
                    },
                    "default_value": "",
                    "placeholder": ""
                }
            ]
        },
        {
            "key": "field_65be98b8bf3b6",
            "label": "Соцсети",
            "name": "social_networks",
            "aria-label": "",
            "type": "repeater",
            "instructions": "",
            "required": 0,
            "conditional_logic": 0,
            "wrapper": {
                "width": "",
                "class": "",
                "id": ""
            },
            "layout": "table",
            "pagination": 0,
            "min": 0,
            "max": 0,
            "collapsed": "",
            "button_label": "Добавить",
            "rows_per_page": 20,
            "sub_fields": [
                {
                    "key": "field_65be98d7bf3b7",
                    "label": "Платформа",
                    "name": "platform",
                    "aria-label": "",
                    "type": "select",
                    "instructions": "",
                    "required": 0,
                    "conditional_logic": 0,
                    "wrapper": {
                        "width": "",
                        "class": "",
                        "id": ""
                    },
                    "choices": {
                        "facebook": "Facebook",
                        "instagram": "Instagram",
                        "linkedin": "LinkedIn",
                        "telegram": "Telegram",
                        "tiktok": "TikTok",
                        "vk": "ВКонтакте",
                        "whatsapp": "WhatsApp",
                        "youtube": "YouTube"
                    },
                    "default_value": false,
                    "return_format": "array",
                    "multiple": 0,
                    "allow_null": 0,
                    "ui": 0,
                    "ajax": 0,
                    "placeholder": "",
                    "parent_repeater": "field_65be98b8bf3b6"
                },
                {
                    "key": "field_65be98febf3b8",
                    "label": "Ссылка",
                    "name": "url",
                    "aria-label": "",
                    "type": "url",
                    "instructions": "",
                    "required": 0,
                    "conditional_logic": 0,
                    "wrapper": {
                        "width": "",
                        "class": "",
                        "id": ""
                    },
                    "default_value": "",
                    "placeholder": "",
                    "parent_repeater": "field_65be98b8bf3b6"
                }
            ]
        }
    ],
    "location": [
        [
            {
                "param": "options_page",
                "operator": "==",
                "value": "morph-settings"
            }
        ]
    ],
    "menu_order": 0,
    "position": "normal",
    "style": "default",
    "label_placement": "top",
    "instruction_placement": "label",
    "hide_on_screen": "",
    "active": true,
    "description": "",
    "show_in_rest": 0,
    "modified": 1706994113
}
